flake8_tensors/__init__.py
flake8_tensors/plugin.py
flake8_tensors/rules.py
flake8_tensors-1.3.1.dist-info/WHEEL
flake8_tensors-1.3.1.dist-info/entry_points.txt
flake8_tensors-1.3.1.dist-info/METADATA
flake8_tensors-1.3.1.dist-info/RECORD
