Metadata-Version: 2.3
Name: flake8-tensors
Version: 1.3.1
Summary: flake8_tensors - flake8 plugin for deep learning codes
Keywords: flake8,deep learning,pytorch,numpy
Author: David Völgyes
Author-email: David Völgyes <david.volgyes@ieee.org>
License: MIT
Requires-Dist: flake8>=7.0,<8.0
Requires-Dist: ruamel-yaml~=0.17.21
Requires-Dist: astpath~=0.9.1
Requires-Dist: lxml~=6.0
Requires-Python: >=3.10, <3.14
Project-URL: Repository, https://github.com/dvolgyes/flake8_tensors
